pylogcq/__init__.py
pylogcq/cq.py
pylogcq/log_convert.py
tests/__init__.py
tests/test_cq.py
tests/test_log-convert.py
pylogcq-0.8.6.dist-info/LICENSE
pylogcq-0.8.6.dist-info/METADATA
pylogcq-0.8.6.dist-info/WHEEL
pylogcq-0.8.6.dist-info/entry_points.txt
pylogcq-0.8.6.dist-info/top_level.txt
pylogcq-0.8.6.dist-info/RECORD
