Metadata-Version: 2.1
Name: pylogcq
Version: 0.8.6
Summary: A simple curses based log for amateur radio use
Home-page: https://github.com/tcarwash/pylogcq
Author: Tyler Carr
Author-email: tcarwash@gmail.com
License: UNKNOWN
Project-URL: Bug Tracker, https://github.com/tcarwash/pylogcq
Platform: UNKNOWN
Classifier: Programming Language :: Python :: 3
Classifier: License :: OSI Approved :: MIT License
Classifier: Operating System :: OS Independent
Requires-Python: >=3.5
License-File: LICENSE
Requires-Dist: adif-io (>=0.0.3)
Requires-Dist: npyscreen (>=4.10.5)
